veeam_easy_connect/__init__.py
veeam_easy_connect/__main__.py
veeam_easy_connect/api_settings.py
veeam_easy_connect-0.8.0.dist-info/LICENSE
veeam_easy_connect-0.8.0.dist-info/METADATA
veeam_easy_connect-0.8.0.dist-info/WHEEL
veeam_easy_connect-0.8.0.dist-info/top_level.txt
veeam_easy_connect-0.8.0.dist-info/RECORD
