Metadata-Version: 2.1
Name: veeam-easy-connect
Version: 0.8.0
Summary: Makes Veeam APIs easier
Home-page: https://github.com/shapedthought/veeam-easy-connect
Author: Ed Howard
Author-email: exfhoward@protonmail.com
License: UNKNOWN
Platform: UNKNOWN
Classifier: Programming Language :: Python :: 3
Classifier: License :: OSI Approved :: MIT License
Classifier: Operating System :: OS Independent
Requires-Python: >=3.6
License-File: LICENSE
Requires-Dist: requests (<3.0.0,>=2.27.1)
